pybioimageutils-0.0.1.dist-info/METADATA
pybioimageutils-0.0.1.dist-info/WHEEL
pybioimageutils-0.0.1.dist-info/entry_points.txt
pybioimageutils-0.0.1.dist-info/licenses/LICENSE
pybioimageutils/__init__.py
pybioimageutils/visualize.py
pybioimageutils-0.0.1.dist-info/RECORD
