Metadata-Version: 2.4
Name: PyBioImageUtils
Version: 0.0.1
Summary: Utilities for bioimaging and bioimage analysis workflows.
Author-Email: Jian Wei Tay <jianweitay@outlook.com>
License-Expression: MIT
License-File: LICENSE
Classifier: Programming Language :: Python :: 3
Classifier: Operating System :: OS Independent
Project-URL: Homepage, https://github.com/jwtay1/PyBioImageUtils
Project-URL: Issues, https://github.com/jwtay1/PyBioImageUtils/issues
Requires-Python: >=3.9
